haul/__init__.py
haul/_util.py
haul/cli.py
haul/errors.py
haul/policy.py
haul/serializers.py
haul/types.py
haul/containers/__init__.py
haul/containers/_export.py
haul/containers/_import.py
haul/containers/_yaml.py
haul/containers/base.py
django_haul-0.1.0.dist-info/LICENSE
django_haul-0.1.0.dist-info/METADATA
django_haul-0.1.0.dist-info/WHEEL
django_haul-0.1.0.dist-info/top_level.txt
django_haul-0.1.0.dist-info/RECORD
