Metadata-Version: 2.1
Name: django-haul
Version: 0.1.0
Summary: Structured object import/export for Django ORM
Home-page: https://github.com/elements-storage/haul
Author: Eugene Pankov`
Author-email: e.pankov@elements.tv
License: MIT
Keywords: django,orm,export,import
Classifier: Development Status :: 2 - Pre-Alpha
Classifier: Intended Audience :: Developers
Classifier: License :: OSI Approved :: MIT License
Classifier: Natural Language :: English
Classifier: Programming Language :: Python :: 3
Classifier: Programming Language :: Python :: 3.7
Classifier: Programming Language :: Python :: 3.8
Requires-Python: >=3.7
License-File: LICENSE
Requires-Dist: django >=3
Requires-Dist: djangorestframework >=3
Requires-Dist: ruamel.yaml >=0.17
Requires-Dist: graphlib-backport ; python_version < "3.9"
